unit_converter/__init__.py
unit_converter/unit_converter.py
unitcvtr-0.0.2.dist-info/LICENSE
unitcvtr-0.0.2.dist-info/METADATA
unitcvtr-0.0.2.dist-info/WHEEL
unitcvtr-0.0.2.dist-info/top_level.txt
unitcvtr-0.0.2.dist-info/RECORD
