Metadata-Version: 2.1
Name: unitcvtr
Version: 0.0.2
Summary: package to convert units
Home-page: UNKNOWN
Author: UndefinedRekian (Rekian Dewandaru)
Author-email: <rekian.fajar@aqi.com>
License: UNKNOWN
Keywords: python,unit,math,convert
Platform: UNKNOWN
Classifier: Development Status :: 1 - Planning
Classifier: Intended Audience :: Developers
Classifier: Programming Language :: Python :: 3
Classifier: Operating System :: Unix
Classifier: Operating System :: MacOS :: MacOS X
Classifier: Operating System :: Microsoft :: Windows
